Metadata-Version: 2.1
Name: brainfuck-interpreter
Version: 1.0.0
Summary: An object-oriented highly flexible brainfuck interpreter.
Home-page: https://github.com/DismissedGuy/brainfuck-interpreter
Author: Mike A.
Author-email: dismissed.is.a.guy@gmail.com
License: UNKNOWN
Platform: UNKNOWN
Classifier: Programming Language :: Python :: 3
Classifier: License :: OSI Approved :: GNU General Public License v3 (GPLv3)
Classifier: Operating System :: OS Independent
Classifier: Topic :: Software Development :: Interpreters
Requires-Python: >=3.6
